cnxrecipes/__init__.py
cnxrecipes/_version.py
cnxrecipes/recipes/TEAap-biology.css
cnxrecipes/recipes/TEAap-physics.css
cnxrecipes/recipes/TEAeconomics.css
cnxrecipes/recipes/TEAhs-physics.css
cnxrecipes/recipes/TEAstatistics.css
cnxrecipes/recipes/_example.css
cnxrecipes/recipes/accounting-prod.css
cnxrecipes/recipes/accounting.css
cnxrecipes/recipes/additive-manufacturing.css
cnxrecipes/recipes/american-government-prod.css
cnxrecipes/recipes/american-government.css
cnxrecipes/recipes/anatomy-prod.css
cnxrecipes/recipes/anatomy.css
cnxrecipes/recipes/anthropology.css
cnxrecipes/recipes/ap-biology-prod.css
cnxrecipes/recipes/ap-biology.css
cnxrecipes/recipes/ap-history-prod.css
cnxrecipes/recipes/ap-history.css
cnxrecipes/recipes/ap-physics-prod.css
cnxrecipes/recipes/ap-physics.css
cnxrecipes/recipes/astronomy-prod.css
cnxrecipes/recipes/astronomy.css
cnxrecipes/recipes/bca.css
cnxrecipes/recipes/biology-prod.css
cnxrecipes/recipes/biology.css
cnxrecipes/recipes/business-ethics-prod.css
cnxrecipes/recipes/business-ethics.css
cnxrecipes/recipes/calculus-prod.css
cnxrecipes/recipes/calculus.css
cnxrecipes/recipes/chemistry-prod.css
cnxrecipes/recipes/chemistry.css
cnxrecipes/recipes/college-physics-prod.css
cnxrecipes/recipes/college-physics.css
cnxrecipes/recipes/college-success-prod.css
cnxrecipes/recipes/college-success.css
cnxrecipes/recipes/computer-science.css
cnxrecipes/recipes/contemporary-math.css
cnxrecipes/recipes/dev-math-prod.css
cnxrecipes/recipes/dev-math.css
cnxrecipes/recipes/economics-prod.css
cnxrecipes/recipes/economics.css
cnxrecipes/recipes/english-composition.css
cnxrecipes/recipes/entrepreneurship-prod.css
cnxrecipes/recipes/entrepreneurship.css
cnxrecipes/recipes/finance.css
cnxrecipes/recipes/history-prod.css
cnxrecipes/recipes/history.css
cnxrecipes/recipes/hs-physics-prod.css
cnxrecipes/recipes/hs-physics.css
cnxrecipes/recipes/intro-business-prod.css
cnxrecipes/recipes/intro-business.css
cnxrecipes/recipes/manifest.json
cnx_recipes-1.104.1.dist-info/LICENSE
cnx_recipes-1.104.1.dist-info/METADATA
cnx_recipes-1.104.1.dist-info/WHEEL
cnx_recipes-1.104.1.dist-info/top_level.txt
cnx_recipes-1.104.1.dist-info/zip-safe
cnx_recipes-1.104.1.dist-info/RECORD
