Metadata-Version: 2.1
Name: cnx-recipes
Version: 1.104.1
Summary: CSS-transform (CSSt) recipes used to bake openstax books
Home-page: http://github.com/Connexions/cnx-recipes
Author: Connexions/OpenStax Team
Author-email: info@cnx.org
License: LGPL, see also LICENSE.txt
Platform: UNKNOWN
License-File: LICENSE
